igseqanalysis/__init__.py
igseqanalysis/cluster_by_count.py
igseqanalysis/count_unique.py
igseqanalysis/csv2fasta.py
igseqanalysis/format_CDR.py
igseqanalysis/format_cluster.py
igseqanalysis/igblast_IG.py
igseqanalysis/igblast_TCR.py
igseqanalysis/pair_by_id.py
igseqanalysis/parse_igblast.py
igseqanalysis/sequtility.py
igseqanalysis/translate_table.py
igseqanalysis/imgt/ig/edit_imgt_file.pl
igseqanalysis/imgt/ig/germline_kabat.csv
igseqanalysis/imgt/ig/germline_kabatVH.csv
igseqanalysis/imgt/ig/germline_kabatVL.csv
igseqanalysis/imgt/ig/human_D.nhr
igseqanalysis/imgt/ig/human_D.nin
igseqanalysis/imgt/ig/human_D.nog
igseqanalysis/imgt/ig/human_D.nsd
igseqanalysis/imgt/ig/human_D.nsi
igseqanalysis/imgt/ig/human_D.nsq
igseqanalysis/imgt/ig/human_IGHD.nhr
igseqanalysis/imgt/ig/human_IGHD.nin
igseqanalysis/imgt/ig/human_IGHD.nog
igseqanalysis/imgt/ig/human_IGHD.nsd
igseqanalysis/imgt/ig/human_IGHD.nsi
igseqanalysis/imgt/ig/human_IGHD.nsq
igseqanalysis/imgt/ig/human_IGHJ.nhr
igseqanalysis/imgt/ig/human_IGHJ.nin
igseqanalysis/imgt/ig/human_IGHJ.nog
igseqanalysis/imgt/ig/human_IGHJ.nsd
igseqanalysis/imgt/ig/human_IGHJ.nsi
igseqanalysis/imgt/ig/human_IGHJ.nsq
igseqanalysis/imgt/ig/human_IGHV.nhr
igseqanalysis/imgt/ig/human_IGHV.nin
igseqanalysis/imgt/ig/human_IGHV.nog
igseqanalysis/imgt/ig/human_IGHV.nsd
igseqanalysis/imgt/ig/human_IGHV.nsi
igseqanalysis/imgt/ig/human_IGHV.nsq
igseqanalysis/imgt/ig/human_J.nhr
igseqanalysis/imgt/ig/human_J.nin
igseqanalysis/imgt/ig/human_J.nog
igseqanalysis/imgt/ig/human_J.nsd
igseqanalysis/imgt/ig/human_J.nsi
igseqanalysis/imgt/ig/human_J.nsq
igseqanalysis/imgt/ig/human_JL.nhr
igseqanalysis/imgt/ig/human_JL.nin
igseqanalysis/imgt/ig/human_JL.nog
igseqanalysis/imgt/ig/human_JL.nsd
igseqanalysis/imgt/ig/human_JL.nsi
igseqanalysis/imgt/ig/human_JL.nsq
igseqanalysis/imgt/ig/human_V.nhr
igseqanalysis/imgt/ig/human_V.nin
igseqanalysis/imgt/ig/human_V.nog
igseqanalysis/imgt/ig/human_V.nsd
igseqanalysis-0.2.3.dist-info/DESCRIPTION.rst
igseqanalysis-0.2.3.dist-info/METADATA
igseqanalysis-0.2.3.dist-info/RECORD
igseqanalysis-0.2.3.dist-info/WHEEL
igseqanalysis-0.2.3.dist-info/entry_points.txt
igseqanalysis-0.2.3.dist-info/metadata.json
igseqanalysis-0.2.3.dist-info/top_level.txt
